odoo/addons/account_analytic_sequence/README.rst
odoo/addons/account_analytic_sequence/__init__.py
odoo/addons/account_analytic_sequence/__manifest__.py
odoo/addons/account_analytic_sequence/data/sequence.xml
odoo/addons/account_analytic_sequence/i18n/account_analytic_sequence.pot
odoo/addons/account_analytic_sequence/i18n/ca.po
odoo/addons/account_analytic_sequence/i18n/cs_CZ.po
odoo/addons/account_analytic_sequence/i18n/de.po
odoo/addons/account_analytic_sequence/i18n/el_GR.po
odoo/addons/account_analytic_sequence/i18n/es.po
odoo/addons/account_analytic_sequence/i18n/es_EC.po
odoo/addons/account_analytic_sequence/i18n/es_MX.po
odoo/addons/account_analytic_sequence/i18n/fi.po
odoo/addons/account_analytic_sequence/i18n/fr.po
odoo/addons/account_analytic_sequence/i18n/gu_IN.po
odoo/addons/account_analytic_sequence/i18n/hi_IN.po
odoo/addons/account_analytic_sequence/i18n/hr.po
odoo/addons/account_analytic_sequence/i18n/hr_HR.po
odoo/addons/account_analytic_sequence/i18n/nl.po
odoo/addons/account_analytic_sequence/i18n/pt_BR.po
odoo/addons/account_analytic_sequence/i18n/sk_SK.po
odoo/addons/account_analytic_sequence/i18n/sl.po
odoo/addons/account_analytic_sequence/i18n/zh_CN.po
odoo/addons/account_analytic_sequence/models/__init__.py
odoo/addons/account_analytic_sequence/models/account_analytic_account.py
odoo/addons/account_analytic_sequence/static/description/icon.png
odoo11_addon_account_analytic_sequence-11.0.1.0.0.99.dev1.dist-info/METADATA
odoo11_addon_account_analytic_sequence-11.0.1.0.0.99.dev1.dist-info/RECORD
odoo11_addon_account_analytic_sequence-11.0.1.0.0.99.dev1.dist-info/WHEEL
odoo11_addon_account_analytic_sequence-11.0.1.0.0.99.dev1.dist-info/top_level.txt
